vedro_xunit_reporter/__init__.py
vedro_xunit_reporter/py.typed
vedro_xunit_reporter/xunit_reporter.py
vedro_xunit_reporter-0.1.2.dist-info/LICENSE
vedro_xunit_reporter-0.1.2.dist-info/METADATA
vedro_xunit_reporter-0.1.2.dist-info/WHEEL
vedro_xunit_reporter-0.1.2.dist-info/RECORD
