Metadata-Version: 2.1
Name: vedro-xunit-reporter
Version: 0.1.2
Summary: xUnit format reporter for Vedro testing framework
Home-page: https://github.com/mickeystreicher/vedro-xunit-reporter
License: Apache-2.0
Author: Mickey Streicher
Author-email: mickeystreicher@fastmail.us
Requires-Python: >=3.8
Classifier: License :: OSI Approved :: Apache Software License
Classifier: Programming Language :: Python :: 3
Classifier: Programming Language :: Python :: 3.8
Classifier: Programming Language :: Python :: 3.9
Classifier: Programming Language :: Python :: 3.10
Classifier: Programming Language :: Python :: 3.11
Classifier: Programming Language :: Python :: 3.12
Classifier: Typing :: Typed
Requires-Dist: vedro (>=1.9)
Project-URL: Repository, https://github.com/mickeystreicher/vedro-xunit-reporter
